{"Arts and Entertainment": 0, "Music": 1, "Data Visualization": 2, "Exploratory Data Analysis": 3, "Movies and TV Shows": 4, "Artificial Intelligence": 5, "Computer Science": 6, "Beginner": 7, "Literature": 8, "E-Commerce Services": 9, "English": 10, "Business": 11, "Tabular": 12, "Investing": 13, "Automobiles and Vehicles": 14, "Transportation": 15, "Clustering": 16, "Games": 17, "Video Games": 18, "Education": 19, "Universities and Colleges": 20, "Categorical": 21, "Healthcare": 22, "Global": 23, "Finance": 24, "Banking": 25, "Data Cleaning": 26, "Earth and Nature": 27, "Advanced": 28, "Cancer": 29, "Classification": 30, "Medicine": 31, "Data Analytics": 32, "People": 33, "Feature Engineering": 34, "Social Networks": 35, "Deep Learning": 36, "Python": 37, "Neural Networks": 38, "Economics": 39, "Primary and Secondary Schools": 40, "Regression": 41, "News": 42, "Biology": 43, "Animals": 44, "Health": 45, "Social Science": 46, "Health Conditions": 47, "Audio": 48, "Food": 49, "Sports": 50, "Football": 51, "Law": 52, "Science and Technology": 53, "Standardized Testing": 54, "Binary Classification": 55, "Retail and Shopping": 56, "United States": 57, "Employment": 58, "Text": 59, "Internet": 60, "Programming": 61, "Intermediate": 62, "Languages": 63, "Linguistics": 64, "Ratings and Reviews": 65, "NLP": 66, "Exercise": 67, "Online Communities": 68, "Asia": 69, "Electronics": 70, "Public Health": 71, "Time Series Analysis": 72, "Image": 73, "Computer Vision": 74, "Diseases": 75, "Politics": 76, "Research": 77, "Currencies and Foreign Exchange": 78, "Statistical Analysis": 79, "Image Classification": 80, "India": 81, "Software": 82, "Linear Regression": 83, "Text Mining": 84, "Recommender Systems": 85, "pandas": 86, "Multiclass Classification": 87, "Government": 88, "GPU": 89, "Jobs and Career": 90, "CNN": 91, "Object Detection": 92, "Agriculture": 93, "Coronavirus": 94, "Video": 95, "Transfer Learning": 96, "Art": 97, "Pre-Trained Model": 98, "Image Segmentation": 99, "TensorFlow": 100, "R": 101, "PyTorch": 102}